LICENSE
MANIFEST.in
NEWS
README
setup.py
docs/Makefile
docs/imapproc.1
docs/imapproc.1.rst
docs/index.html
docs/index.rst
docs/maildirproc.1
docs/maildirproc.1.rst
docs/mailprocessing.5
docs/mailprocessing.5.rst
docs/mailprocessing.css
docs/reference.html
docs/reference.rst
docs/examples/bogofilter.rc
docs/examples/complex.rc
docs/examples/index.html
docs/examples/logrotate.conf.continuous
docs/examples/logrotate.conf.once
docs/examples/medium.rc
docs/examples/simple.rc
docs/examples/sketchy.rc
docs/pandoc/README.md
docs/pandoc/delink.py
docs/reference/config.rst
docs/reference/description_imapproc.rst
docs/reference/description_maildirproc.rst
docs/reference/options_common.rst
docs/reference/options_imapproc.rst
docs/reference/options_maildirproc.rst
mailprocessing/__init__.py
mailprocessing/signals.py
mailprocessing/util.py
mailprocessing/version.py
mailprocessing.egg-info/PKG-INFO
mailprocessing.egg-info/SOURCES.txt
mailprocessing.egg-info/dependency_links.txt
mailprocessing.egg-info/entry_points.txt
mailprocessing.egg-info/top_level.txt
mailprocessing/cmd/__init__.py
mailprocessing/cmd/imap.py
mailprocessing/cmd/maildir.py
mailprocessing/mail/__init__.py
mailprocessing/mail/base.py
mailprocessing/mail/dryrun.py
mailprocessing/mail/header.py
mailprocessing/mail/imap.py
mailprocessing/mail/maildir.py
mailprocessing/mail/target.py
mailprocessing/processor/__init__.py
mailprocessing/processor/generic.py
mailprocessing/processor/imap.py
mailprocessing/processor/maildir.py